pyfva/__init__.py
pyfva/constants.py
pyfva/logger.py
pyfva/test.py
pyfva/clientes/__init__.py
pyfva/clientes/autenticador.py
pyfva/clientes/firmador.py
pyfva/clientes/validador.py
pyfva/clientes/validator.py
pyfva/clientes/verificador.py
pyfva/receptor/__init__.py
pyfva/receptor/client.py
pyfva/receptor/ws_service.py
pyfva/soap/__init__.py
pyfva/soap/autenticador.py
pyfva/soap/firmador.py
pyfva/soap/receptor.py
pyfva/soap/settings.py
pyfva/soap/validador_certificado.py
pyfva/soap/validador_documento.py
pyfva/soap/verificador.py
pyfva-0.0.35.dist-info/LICENSE
pyfva-0.0.35.dist-info/METADATA
pyfva-0.0.35.dist-info/WHEEL
pyfva-0.0.35.dist-info/top_level.txt
pyfva-0.0.35.dist-info/RECORD
