Metadata-Version: 2.1
Name: pyfva
Version: 0.0.35
Summary: Cliente para conectar instituciones con BCCR FVA.
Home-page: https://github.com/solvo/pyfva
Author: Luis Zarate Montero
Author-email: luis.zarate@solvosoft.com
License: GNU General Public License
Platform: OS Independent
Classifier: Intended Audience :: Developers
Classifier: License :: OSI Approved :: GNU General Public License v3 or later (GPLv3+)
Classifier: Operating System :: OS Independent
Classifier: Programming Language :: Python
Classifier: Programming Language :: Python :: 3.4
Classifier: Programming Language :: Python :: 3.5
Classifier: Topic :: Internet :: WWW/HTTP
Classifier: Topic :: Internet :: WWW/HTTP :: Dynamic Content
